empressia_sqlalchemy_h2/CompatibilityMode.py
empressia_sqlalchemy_h2/H2Dialect.py
empressia_sqlalchemy_h2/H2DialectException.py
empressia_sqlalchemy_h2/__init__.py
empressia_sqlalchemy_h2/test/Utilities.py
empressia_sqlalchemy_h2/test/__init__.py
empressia_sqlalchemy_h2-1.0.2.dist-info/METADATA
empressia_sqlalchemy_h2-1.0.2.dist-info/WHEEL
empressia_sqlalchemy_h2-1.0.2.dist-info/licenses/LICENSE.txt
empressia_sqlalchemy_h2-1.0.2.dist-info/RECORD
