Metadata-Version: 2.4
Name: Empressia-SQLAlchemy-H2
Version: 1.0.2
Summary: Empressia製のSQLAlchemy用のDialectです。 H2 DatabaseへのJayDeBeApiを使用したJDBC接続をサポートします。
Project-URL: Homepage, https://github.com/Empressia/EmpressiaSQLAlchemyH2/
Author: すふぃあ
Maintainer: すふぃあ
License-Expression: MIT
License-File: LICENSE.txt
Keywords: Empressia,H2 Database,JDBC,JayDeBeApi,SQLAlchemy
Classifier: Topic :: Database
Requires-Python: >=3.10
Requires-Dist: jaydebeapi>=1.2.3
Requires-Dist: sqlalchemy>=2.0
